[{"feature":"지면온도(°C)_3일_평균","importance":0.511609},{"feature":"강수량(mm)_7일_합","importance":0.135834},{"feature":"전기전도도_이전_30","importance":0.084206},{"feature":"전기전도도_이전_14","importance":0.056},{"feature":"수온","importance":0.05046},{"feature":"전기전도도","importance":0.038564},{"feature":"전기전도도_이전_3","importance":0.018365},{"feature":"월","importance":0.017856},{"feature":"전기전도도_이전_1","importance":0.016999},{"feature":"월_사인","importance":0.016894},{"feature":"전기전도도_이전_7","importance":0.01363},{"feature":"월_코사인","importance":0.01197},{"feature":"일","importance":0.011556},{"feature":"기온(°C)_3일_평균","importance":0.008957},{"feature":"수리전도도_강수_지표","importance":0.00215},{"feature":"강수량(mm)_3일_합","importance":0.002009},{"feature":"현지기압(hPa)","importance":0.001371},{"feature":"기온(°C)","importance":0.000258},{"feature":"순강수량","importance":0.000236},{"feature":"풍속(m/s)","importance":0.000123},{"feature":"상대습도","importance":0.000104},{"feature":"잠재증발량","importance":0.000099},{"feature":"기압_변화량","importance":0.000094},{"feature":"습도(%)","importance":0.000082},{"feature":"온도차","importance":0.000078},{"feature":"지면온도(°C)","importance":0.000074},{"feature":"강수량(mm)","importance":0.000068},{"feature":"강수량_표고_상호","importance":0.000054},{"feature":"강수량(mm)_이전_7","importance":0.000048},{"feature":"시간","importance":0.000048},{"feature":"시간_코사인","importance":0.000044},{"feature":"전기전도도_변화량","importance":0.000042},{"feature":"강수량(mm)_lag_3","importance":0.000034},{"feature":"시간_사인","importance":0.000033},{"feature":"강수량(mm)_이전_1","importance":0.000024},{"feature":"강수량(mm)_이전_14","importance":0.000015},{"feature":"강수량(mm)_이전_30","importance":0.000012}]